Orange_Network-0.3.5-py2.7-nspkg.pth
Orange_Network-0.3.5.dist-info/DESCRIPTION.rst
Orange_Network-0.3.5.dist-info/METADATA
Orange_Network-0.3.5.dist-info/RECORD
Orange_Network-0.3.5.dist-info/WHEEL
Orange_Network-0.3.5.dist-info/entry_points.txt
Orange_Network-0.3.5.dist-info/metadata.json
Orange_Network-0.3.5.dist-info/namespace_packages.txt
Orange_Network-0.3.5.dist-info/top_level.txt
orangecontrib/network/__init__.py
orangecontrib/network/community.py
orangecontrib/network/network.py
orangecontrib/network/readwrite.py
orangecontrib/network/snap.py
orangecontrib/network/networks/airtraffic.net
orangecontrib/network/networks/airtraffic_items.tab
orangecontrib/network/networks/dicty_publication.net
orangecontrib/network/networks/dicty_publication_edges.tab
orangecontrib/network/networks/dicty_publication_items.tab
orangecontrib/network/networks/lastfm.net
orangecontrib/network/networks/lastfm.tab
orangecontrib/network/networks/lastfm_all.tab
orangecontrib/network/networks/lastfm_tags.tab
orangecontrib/network/networks/leu_by_genesets.net
orangecontrib/network/networks/leu_by_genesets_items.tab
orangecontrib/network/networks/leu_by_pmid.net
orangecontrib/network/networks/leu_by_pmid_items.tab
orangecontrib/network/networks/leu_huttenhower_a.net
orangecontrib/network/networks/leu_huttenhower_a_items.tab
orangecontrib/network/networks/makeNetworkList.py
orangecontrib/network/networks/mips_c2_cp_leu.net
orangecontrib/network/networks/mips_c2_cp_leu_items.tab
orangecontrib/network/networks/network_info.tab
orangecontrib/network/networks/pubmed.gpickle
orangecontrib/network/widgets/OWNxAnalysis.py
orangecontrib/network/widgets/OWNxCanvasQt.py
orangecontrib/network/widgets/OWNxClustering.py
orangecontrib/network/widgets/OWNxExplorer.py
orangecontrib/network/widgets/OWNxFile.py
orangecontrib/network/widgets/OWNxFromDistances.py
orangecontrib/network/widgets/OWNxHist.py
orangecontrib/network/widgets/OWNxInsideView.py
orangecontrib/network/widgets/OWNxSNAP.py
orangecontrib/network/widgets/OWPubmedView.py
orangecontrib/network/widgets/__init__.py
orangecontrib/network/widgets/files/network-K5-fr.png
orangecontrib/network/widgets/files/network-K5-random.png
orangecontrib/network/widgets/files/network-explorer.png
orangecontrib/network/widgets/files/network-subgraph.png
