Metadata-Version: 2.0
Name: Orange-Network
Version: 0.3.5
Summary: Orange Network add-on for Orange data mining software package.
Home-page: http://orange.biolab.si/addons/
Author: Miha Stajdohar, FRI UL
Author-email: miha.stajdohar@gmail.com
License: GPLv3
Download-URL: https://bitbucket.org/mstajdohar/orange-network/downloads
Keywords: network,network analysis,network layout,network visualization,data mining,machine learning,artificial intelligence,orange,orange add-on
Platform: UNKNOWN
Classifier: Development Status :: 4 - Beta
Classifier: Environment :: X11 Applications :: Qt
Classifier: Environment :: Console
Classifier: Environment :: Plugins
Classifier: Programming Language :: Python
Classifier: License :: OSI Approved :: GNU General Public License v3 or later (GPLv3+)
Classifier: Operating System :: OS Independent
Classifier: Topic :: Scientific/Engineering :: Artificial Intelligence
Classifier: Topic :: Scientific/Engineering :: Visualization
Classifier: Topic :: Software Development :: Libraries :: Python Modules
Classifier: Intended Audience :: Education
Classifier: Intended Audience :: Science/Research
Classifier: Intended Audience :: Developers
Requires-Dist: Orange
Requires-Dist: networkx
Requires-Dist: pyparsing (>=2.0.1)
Provides-Extra: GUI
Requires-Dist: PyQt4; extra == 'GUI'
Provides-Extra: reST
Requires-Dist: numpydoc; extra == 'reST'
